spider_web/__init__.py
spider_web/netstat_no_cli.py
spider_web/record_netstat.py
spider_web/utils/__init__.py
spider_web/utils/file_utils.py
spider_web-0.0.5.dist-info/LICENSE.md
spider_web-0.0.5.dist-info/METADATA
spider_web-0.0.5.dist-info/WHEEL
spider_web-0.0.5.dist-info/entry_points.txt
spider_web-0.0.5.dist-info/top_level.txt
spider_web-0.0.5.dist-info/RECORD
