Metadata-Version: 2.1
Name: spider-web
Version: 0.0.5
Summary: CLI for catching bugs on a computer system
Home-page: https://codeberg.org/cap_jmk/spider-web.git
Author: Julian M. Kleber
Author-email: julian.kleber@sail.black
Classifier: Programming Language :: Python :: 3
Classifier: License :: OSI Approved :: GNU General Public License v3 (GPLv3)
Classifier: Operating System :: OS Independent
Requires-Python: >=3.9
License-File: LICENSE.md
Requires-Dist: Click
